pandas_selectable/__init__.py
pandas_selectable-1.2.0.dist-info/LICENSE
pandas_selectable-1.2.0.dist-info/METADATA
pandas_selectable-1.2.0.dist-info/WHEEL
pandas_selectable-1.2.0.dist-info/top_level.txt
pandas_selectable-1.2.0.dist-info/RECORD
