Metadata-Version: 2.1
Name: pandas_selectable
Version: 1.2.0
Summary: Add a select accessor to pandas
Home-page: https://github.com/jseabold/pandas-selectable
Author: Skipper Seabold
Classifier: Programming Language :: Python :: 3
Classifier: License :: OSI Approved :: MIT License
Requires-Python: >=3.6
License-File: LICENSE
